lakescum/__init__.py
lakescum-0.1.3.dist-info/LICENSE
lakescum-0.1.3.dist-info/METADATA
lakescum-0.1.3.dist-info/WHEEL
lakescum-0.1.3.dist-info/RECORD
