Metadata-Version: 2.1
Name: lakescum
Version: 0.1.3
Summary: A Python pacakge to help Databricks Unity Catalog users to read and query Delta Lake tables with `Polars`, `DuckDb`, or `PyArrow`.
Author: Daniel Beach
Author-email: dancrystalbeach@gmail.com
Requires-Python: >=3.8,<4.0
Classifier: Programming Language :: Python :: 3
Classifier: Programming Language :: Python :: 3.8
Classifier: Programming Language :: Python :: 3.9
Classifier: Programming Language :: Python :: 3.10
Classifier: Programming Language :: Python :: 3.11
Classifier: Programming Language :: Python :: 3.12
Requires-Dist: deltalake (>=0.16.2,<0.17.0)
Requires-Dist: duckdb (>=0.10.1,<0.11.0)
Requires-Dist: polars (>=0.20.16,<0.21.0)
Requires-Dist: pyarrow (>=15.0.2,<16.0.0)
